gym_softrobot/__init__.py
gym_softrobot/config.py
gym_softrobot/version.py
gym_softrobot/debug/__init__.py
gym_softrobot/debug/make.py
gym_softrobot/debug/registry.py
gym_softrobot/debug/render.py
gym_softrobot/envs/__init__.py
gym_softrobot/envs/octopus/__init__.py
gym_softrobot/envs/octopus/arm_push_env.py
gym_softrobot/envs/octopus/arm_single_env.py
gym_softrobot/envs/octopus/arm_two_env.py
gym_softrobot/envs/octopus/build.py
gym_softrobot/envs/octopus/build_muscle_octopus.py
gym_softrobot/envs/octopus/controllable_constraint.py
gym_softrobot/envs/octopus/crawl_env.py
gym_softrobot/envs/octopus/flat_3d_env.py
gym_softrobot/envs/octopus/flat_env.py
gym_softrobot/envs/octopus/hunt_env.py
gym_softrobot/envs/octopus/reach_env.py
gym_softrobot/envs/octopus/swim_env.py
gym_softrobot/envs/simple_control/__init__.py
gym_softrobot/envs/simple_control/inertial_pull.py
gym_softrobot/envs/snake/__init__.py
gym_softrobot/envs/snake/continuum_snake.py
gym_softrobot/envs/soft_arm/__init__.py
gym_softrobot/envs/soft_arm/soft_arm_tracking.py
gym_softrobot/envs/soft_arm/soft_arm_tracking_legacy.py
gym_softrobot/envs/soft_arm/train_code.py
gym_softrobot/envs/soft_pendulum/__init__.py
gym_softrobot/envs/soft_pendulum/build.py
gym_softrobot/envs/soft_pendulum/soft_pendulum.py
gym_softrobot/utils/__init__.py
gym_softrobot/utils/intersection.py
gym_softrobot/utils/actuation/__init__.py
gym_softrobot/utils/actuation/frame_tools.py
gym_softrobot/utils/actuation/rod_tools.py
gym_softrobot/utils/actuation/actuations/__init__.py
gym_softrobot/utils/actuation/actuations/actuation.py
gym_softrobot/utils/actuation/actuations/muscles/__init__.py
gym_softrobot/utils/actuation/actuations/muscles/longitudinal_muscle.py
gym_softrobot/utils/actuation/actuations/muscles/muscle.py
gym_softrobot/utils/actuation/actuations/muscles/oblique_muscle.py
gym_softrobot/utils/actuation/actuations/muscles/transverse_muscle.py
gym_softrobot/utils/actuation/algorithms/__init__.py
gym_softrobot-0.1.4.dist-info/LICENSE
gym_softrobot-0.1.4.dist-info/METADATA
gym_softrobot-0.1.4.dist-info/WHEEL
gym_softrobot-0.1.4.dist-info/top_level.txt
gym_softrobot-0.1.4.dist-info/RECORD
