Metadata-Version: 2.1
Name: gym-softrobot
Version: 0.1.4
Summary: Soft-robotics control environment package for OpenAI Gym
Home-page: https://github.com/skim0119/gym-softrobot
Author: skim0119
Author-email: skim449@illinois.edu
License: MIT
Download-URL: https://github.com/skim0119/gym-softrobot/archive/refs/tags/v0.1.4.tar.gz
Platform: UNKNOWN
Classifier: License :: OSI Approved :: MIT License
Classifier: Development Status :: 2 - Pre-Alpha
Classifier: Framework :: Robot Framework :: Library
Classifier: Programming Language :: Python :: 3.8
Classifier: Intended Audience :: Science/Research
Classifier: Intended Audience :: Education
Requires-Python: >=3.8.0
License-File: LICENSE
Requires-Dist: gym (>=0.21.0)
Requires-Dist: pyelastica (>=0.2.0)
Requires-Dist: matplotlib (>=3.3.2)
Requires-Dist: pyglet (>=1.4.0)
Requires-Dist: vapory
